Workbook

Sheet Master Overview
A1: 📊 TakeOnTime / FOOD ORDERING APP — Full Project Task Tracker | FlutterFlow · Supabase · FCM · Razorpay
A2: All Sheets: UI/UX · Database · Backend · FlutterFlow · QA · Security | 12-Week MVP Roadmap
A4: # | B4: Team / Role | C4: Responsibilities | D4: Sheet Name | E4: Total Tasks | F4: Not Started | G4: In Progress | H4: In Review | I4: Done | J4: Blocked | K4: % Complete
A5: 1 | B5: 🎨 UI/UX Designer | C5: Figma screens, design system, prototypes, handoff | D5: UI-UX Design | E5: =COUNTA('UI-UX Design'!D4:D19) -> 16 | F5: =COUNTIF('UI-UX Design'!I4:I19,"Not Started") -> 16 | G5: =COUNTIF('UI-UX Design'!I4:I19,"In Progress") -> 0 | H5: =COUNTIF('UI-UX Design'!I4:I19,"In Review") -> 0 | I5: =COUNTIF('UI-UX Design'!I4:I19,"Done") -> 0 | J5: =COUNTIF('UI-UX Design'!I4:I19,"Blocked") -> 0 | K5: =IFERROR(I5/E5,"—") -> 0
A6: 2 | B6: 🗄️ DB Engineer | C6: Supabase schema, RLS, functions, migrations, optimisation | D6: Database | E6: =COUNTA(Database!D4:D19) -> 16 | F6: =COUNTIF(Database!I4:I19,"Not Started") -> 16 | G6: =COUNTIF(Database!I4:I19,"In Progress") -> 0 | H6: =COUNTIF(Database!I4:I19,"In Review") -> 0 | I6: =COUNTIF(Database!I4:I19,"Done") -> 0 | J6: =COUNTIF(Database!I4:I19,"Blocked") -> 0 | K6: =IFERROR(I6/E6,"—") -> 0
A7: 3 | B7: ⚙️ Backend Engineer | C7: Edge Functions, payments, notifications, settlement engine | D7: Backend | E7: =COUNTA(Backend!D4:D19) -> 16 | F7: =COUNTIF(Backend!I4:I19,"Not Started") -> 16 | G7: =COUNTIF(Backend!I4:I19,"In Progress") -> 0 | H7: =COUNTIF(Backend!I4:I19,"In Review") -> 0 | I7: =COUNTIF(Backend!I4:I19,"Done") -> 0 | J7: =COUNTIF(Backend!I4:I19,"Blocked") -> 0 | K7: =IFERROR(I7/E7,"—") -> 0
A8: 4 | B8: 🔧 FlutterFlow Dev | C8: Customer/Vendor/Admin build, Supabase connect, screens, actions, deploy | D8: FlutterFlow | E8: =COUNTA(FlutterFlow!D4:D24) -> 21 | F8: =COUNTIF(FlutterFlow!I4:I24,"Not Started") -> 21 | G8: =COUNTIF(FlutterFlow!I4:I24,"In Progress") -> 0 | H8: =COUNTIF(FlutterFlow!I4:I24,"In Review") -> 0 | I8: =COUNTIF(FlutterFlow!I4:I24,"Done") -> 0 | J8: =COUNTIF(FlutterFlow!I4:I24,"Blocked") -> 0 | K8: =IFERROR(I8/E8,"—") -> 0
B9: TOTAL | E9: =SUM(E5:E8) -> 69 | F9: =SUM(F5:F8) -> 69 | G9: =SUM(G5:G8) -> 0 | H9: =SUM(H5:H8) -> 0 | I9: =SUM(I5:I8) -> 0 | J9: =SUM(J5:J8) -> 0 | K9: =IFERROR(I9/E9,"—") -> 0
A11: PHASES AT A GLANCE (1 phase = 1 week, per SRS Section 6)
A12: Phase | B12: Name | C12: Timeline | D12: What Happens
A13: Phase 0 | B13: Database & Project Setup | C13: Week 1 | D13: Backend-only: Supabase project, core schema, storage buckets, baseline RLS
A14: Phase 1 | B14: Authentication & Roles | C14: Week 2 | D14: Customer/Vendor/Admin login, RLS tested for all roles
A15: Phase 2 | B15: Vendor Onboarding & Organization | C15: Week 3 | D15: Register, documents, bank integration, branch setup, organization
A16: Phase 3 | B16: Menu Management | C16: Week 4 | D16: Categories, products, availability windows, store/inventory toggles
A17: Phase 4 | B17: Customer Discovery & Browsing | C17: Week 5 | D17: Vendor list, menu, product detail, geofenced marketplace
A18: Phase 5 | B18: Cart, Checkout & Payments + Self-Cancellation | C18: Week 6 | D18: Razorpay + COD checkout, invoice, 2-min self-cancel window
A19: Phase 6 | B19: Vendor Live Order Management | C19: Week 7 | D19: Order queue, accept/prep time, cancel + refund flows
A20: Phase 7 | B20: Customer Tracking & Notifications | C20: Week 8 | D20: Live tracker, ETA, OTP/QR pickup, FCM pushes
A21: Phase 8 | B21: Finance Engine | C21: Week 9 | D21: Settlement engine, COD reconciliation, cancellation refund logic
A22: Phase 9 | B22: Reports & Dashboards | C22: Week 10 | D22: Vendor earnings dashboard, exportable reports, order history
A23: Phase 10 | B23: Admin Panel | C23: Week 11 | D23: Platform dashboard, charts, top lists, audit log
A24: Phase 11 | B24: Testing, QA & Launch | C24: Week 12 | D24: Full regression, security review, Play Store & App Store submission

Sheet UI-UX Design
A1: 🎨 UI/UX Designer — TakeOnTime App Task Tracker
A2: Figma screens, design system, prototypes, handoff
A3: # | B3: Phase | C3: Week | D3: Task ID | E3: Task Title | F3: Description | G3: Deliverable / Output | H3: Priority | I3: Status | J3: Assigned To | K3: Depends On | L3: Est. Hours | M3: Actual Hours | N3: Notes
A4: 1 | B4: Phase 0 | C4: W1 | D4: UX-001 | E4: Design System & Style Guide | F4: Define colour palette, typography, spacing grid, icon set, component tokens for Customer/Vendor/Admin apps | G4: design-system Figma file | H4: High | I4: Not Started | J4: UI/UX Designer | K4: — | L4: 16
A5: 2 | B5: Phase 0 | C5: W1 | D5: UX-002 | E5: App Navigation Wireframes | F5: Wireframe core navigation for Customer app, Vendor dashboard, and Admin panel | G5: Wireframe set | H5: High | I5: Not Started | J5: UI/UX Designer | K5: UX-001 | L5: 10
A6: 3 | B6: Phase 1 | C6: W2 | D6: UX-003 | E6: Customer Onboarding Screens | F6: Design Splash, OTP/Email login, Basic Profile, Organization Selector screens | G6: Onboarding screen frames + prototype | H6: Medium | I6: Not Started | J6: UI/UX Designer | K6: UX-002 | L6: 14
A7: 4 | B7: Phase 1 | C7: W2 | D7: UX-004 | E7: Vendor Onboarding Screens | F7: Design Register, Business Profile, GST Status form, Document Upload screens | G7: Vendor onboarding frames | H7: Medium | I7: Not Started | J7: UI/UX Designer | K7: UX-002 | L7: 14
A8: 5 | B8: Phase 2 | C8: W3 | D8: UX-005 | E8: Vendor Branch & Bank Setup Screens | F8: Design Branch Setup (hours, counter, holidays) and Bank Account Connect screens | G8: Branch/bank screen frames | H8: Medium | I8: Not Started | J8: UI/UX Designer | K8: UX-004 | L8: 8
A9: 6 | B9: Phase 3 | C9: W4 | D9: UX-006 | E9: Vendor Menu Management Screens | F9: Design Category Manager, Product Editor, Availability Window Setting, Store & Inventory Toggles | G9: Menu management frames | H9: Medium | I9: Not Started | J9: UI/UX Designer | K9: UX-004 | L9: 16
A10: 7 | B10: Phase 4 | C10: W5 | D10: UX-007 | E10: Customer Discovery Screens | F10: Design Vendor List (search/filter), Menu Screen (time-aware greying), Product Detail | G10: Discovery screen frames | H10: Medium | I10: Not Started | J10: UI/UX Designer | K10: UX-003 | L10: 14
A11: 8 | B11: Phase 5 | C11: W6 | D11: UX-008 | E11: Cart, Checkout & Payment Screens | F11: Design Cart, Checkout (pickup-time picker), Payment Method Selector, Razorpay/COD confirmation screens | G11: Checkout screen frames | H11: Medium | I11: Not Started | J11: UI/UX Designer | K11: UX-007 | L11: 16
A12: 9 | B12: Phase 5 | C12: W6 | D12: UX-009 | E12: Cancel-Order Countdown Component | F12: Design Cancel Order button with a live 2:00 countdown timer for the confirmation/tracking screen | G12: Countdown component + states | H12: Medium | I12: Not Started | J12: UI/UX Designer | K12: UX-008 | L12: 6
A13: 10 | B13: Phase 5 | C13: W6 | D13: UX-010 | E13: Invoice PDF Layout | F13: Design the auto-generated customer invoice layout for both Razorpay (paid) and COD (pay-at-pickup) paths | G13: Invoice template | H13: Medium | I13: Not Started | J13: UI/UX Designer | K13: UX-008 | L13: 6
A14: 11 | B14: Phase 6 | C14: W7 | D14: UX-011 | E14: Vendor Kitchen Display Screens | F14: Design Order Queue (sorted by pickup deadline), Accept Order Modal, Order Card, Cancel/Refund flow | G14: Kitchen display frames | H14: Medium | I14: Not Started | J14: UI/UX Designer | K14: UX-006 | L14: 14
A15: 12 | B15: Phase 7 | C15: W8 | D15: UX-012 | E15: Customer Tracking & Pickup Screens | F15: Design Live Order Tracker, ETA Display, OTP/QR Pickup Screen | G15: Tracking screen frames | H15: Medium | I15: Not Started | J15: UI/UX Designer | K15: UX-007 | L15: 12
... A19: 16 | B19: Phase 11 | C19: W12 | D19: UX-016 | E19: Store Assets & Screenshots | F19: Design Play Store / App Store screenshots, feature graphic, app icon variants | G19: Store graphics package | H19: Medium | I19: Not Started | J19: UI/UX Designer | K19: UX-015 | L19: 8
A21: ="TOTAL TASKS: "&COUNTA(D4:D19)&" | Est. Hours:" -> TOTAL TASKS: 16 | Est. Hours: | L21: =SUM(L4:L19) -> 188

Sheet Database
A1: 🗄️ DB Engineer — TakeOnTime App Task Tracker
A2: Supabase schema, RLS, functions, migrations, optimisation
A3: # | B3: Phase | C3: Week | D3: Task ID | E3: Task Title | F3: Description | G3: Deliverable / Output | H3: Priority | I3: Status | J3: Assigned To | K3: Depends On | L3: Est. Hours | M3: Actual Hours | N3: Notes
A4: 1 | B4: Phase 0 | C4: W1 | D4: DB-001 | E4: Supabase Project Setup | F4: Create Supabase project, configure Auth, Database, Storage, Edge Functions, Realtime, RLS | G4: Supabase project live | H4: Critical | I4: Not Started | K4: — | L4: 4
A5: 2 | B5: Phase 0 | C5: W1 | D5: DB-002 | E5: Design Core Schema (20 tables) | F5: Design and create the core schema per SRS Section 5, including payment_method / payment_status columns | G5: Core schema live | H5: Critical | I5: Not Started | K5: DB-001 | L5: 10
A6: 3 | B6: Phase 0 | C6: W1 | D6: DB-003 | E6: Storage Buckets Setup | F6: Create buckets: product-images, vendor-logos, organization-images, invoices, documents | G6: Storage buckets live | H6: Critical | I6: Not Started | K6: DB-001 | L6: 3
A7: 4 | B7: Phase 0 | C7: W1 | D7: DB-004 | E7: Baseline RLS Policies | F7: Write baseline RLS: Customer → own orders only; Vendor → own branch only; Admin → read everything | G7: RLS policies live | H7: Critical | I7: Not Started | K7: DB-002 | L7: 8
A8: 5 | B8: Phase 1 | C8: W2 | D8: DB-005 | E8: users & vendors Tables | F8: users (role, phone, email, auth fields); vendors (gst_registered, gstin); RLS tested for all 3 roles | G8: Tables + RLS tested | H8: Critical | I8: Not Started | K8: DB-002 | L8: 6
A9: 6 | B9: Phase 2 | C9: W3 | D9: DB-006 | E9: Organization & Vendor Branch Tables | F9: organizations, vendor_organizations, vendor_branches; vendors.documents_url, bank_account_ref | G9: Tables live | H9: Critical | I9: Not Started | K9: DB-002 | L9: 8
A10: 7 | B10: Phase 3 | C10: W4 | D10: DB-007 | E10: Categories & Products Tables | F10: categories; products (price, gst_percent, availability_start/end, stock_status) | G10: Tables live | H10: Critical | I10: Not Started | K10: DB-002 | L10: 6
A11: 8 | B11: Phase 4 | C11: W5 | D11: DB-008 | E11: Geofenced Marketplace Query | F11: Optimised query: vendors visible to a customer by selected organization, with public-browse fallback | G11: Query tested | H11: High | I11: Not Started | K11: DB-006 | L11: 6
A12: 9 | B12: Phase 5 | C12: W6 | D12: DB-009 | E12: Orders, Payments & Invoice Tables | F12: orders (pickup_time, payment_method); order_items; payments (gateway_ref/COD, status, amount); customer_invoices | G12: Tables live | H12: Critical | I12: Not Started | K12: DB-002 | L12: 8
A13: 10 | B13: Phase 5 | C13: W6 | D13: DB-010 | E13: Self-Cancellation Fields | F13: Add orders.customer_cancel_deadline (timestamptz), cancelled_by (enum), cancellable (boolean, default true) | G13: Fields live + tested | H13: Critical | I13: Not Started | K13: DB-009 | L13: 4
A14: 11 | B14: Phase 6 | C14: W7 | D14: DB-011 | E14: Order Status & Notifications Tables | F14: orders (status, prep_time_minutes, cancelled_reason, refund_type); notifications (order-event log) | G14: Tables live | H14: High | I14: Not Started | K14: DB-009 | L14: 6
A15: 12 | B15: Phase 7 | C15: W8 | D15: DB-012 | E15: OTP/QR Pickup Fields | F15: orders.otp_code / qr_token, collected_at; notifications FCM log | G15: Fields live | H15: High | I15: Not Started | K15: DB-009 | L15: 4
... A19: 16 | B19: Phase 11 | C19: W12 | D19: DB-016 | E19: Production Migration & Backup | F19: Numbered idempotent migration script for all tables/RLS/functions; configure production backups | G19: migration_001.sql + backup verified | H19: Critical | I19: Not Started | K19: DB-015 | L19: 8
A21: ="TOTAL TASKS: "&COUNTA(D4:D19)&" | Est. Hours:" -> TOTAL TASKS: 16 | Est. Hours: | L21: =SUM(L4:L19) -> 101

Sheet Backend
A1: ⚙️ Backend Engineer — TakeOnTime App Task Tracker
A2: Edge Functions, payments, notifications, settlement engine
A3: # | B3: Phase | C3: Week | D3: Task ID | E3: Task Title | F3: Description | G3: Deliverable / Output | H3: Priority | I3: Status | J3: Assigned To | K3: Depends On | L3: Est. Hours | M3: Actual Hours | N3: Notes
A4: 1 | B4: Phase 0 | C4: W1 | D4: BE-001 | E4: Razorpay Account & API Keys | F4: Create Razorpay account, generate API keys, store secrets in Supabase Vault | G4: Keys in Vault | H4: Critical | I4: Not Started | K4: — | L4: 3
A5: 2 | B5: Phase 1 | C5: W2 | D5: BE-002 | E5: Edge Function: send_otp / verify_otp | F5: Phone OTP or Email login for Customer, Vendor, Admin roles | G5: Auth functions tested | H5: Critical | I5: Not Started | K5: DB-005 | L5: 8
A6: 3 | B6: Phase 2 | C6: W3 | D6: BE-003 | E6: Edge Function: vendor_document_notify | F6: Notify admin/vendor on document upload; update verification status | G6: Function tested | H6: Critical | I6: Not Started | K6: DB-006 | L6: 6
A7: 4 | B7: Phase 5 | C7: W6 | D7: BE-004 | E7: Edge Function: create_razorpay_order + Webhook | F7: Launch Razorpay checkout, verify webhook signature, create order only on payment success | G7: Function + webhook tested | H7: Critical | I7: Not Started | K7: DB-009 | L7: 12
A8: 5 | B8: Phase 5 | C8: W6 | D8: BE-005 | E8: Edge Function: process_cod_order | F8: Create order immediately with payment_status = pending_cod; mark invoice "Pay at Pickup" | G8: Function tested | H8: Critical | I8: Not Started | K8: DB-009 | L8: 6
A9: 6 | B9: Phase 5 | C9: W6 | D9: BE-006 | E9: Edge Function: generate_invoice | F9: Auto-generate downloadable PDF invoice for both Razorpay and COD payment paths | G9: Function tested | H9: Critical | I9: Not Started | K9: BE-004 | L9: 8
A10: 7 | B10: Phase 5 | C10: W6 | D10: BE-007 | E10: Edge Function: self_cancel_order | F10: 2-minute self-service cancellation: Razorpay auto-refund via API or COD void, before vendor acceptance | G10: Function tested | H10: Critical | I10: Not Started | K10: DB-010 | L10: 10
A11: 8 | B11: Phase 6 | C11: W7 | D11: BE-008 | E11: FCM Push: New Order Notification | F11: Loud, repeating alert to vendor for incoming orders until accepted | G11: Push tested | H11: Critical | I11: Not Started | K11: DB-011 | L11: 6
A12: 9 | B12: Phase 6 | C12: W7 | D12: BE-009 | E12: Edge Function: cancel_order (vendor-initiated) | F12: Vendor cancellation with auto digital refund or manually logged cash refund | G12: Function tested | H12: Critical | I12: Not Started | K12: BE-007 | L12: 6
A13: 10 | B13: Phase 7 | C13: W8 | D13: BE-010 | E13: FCM Push: Order Lifecycle Notifications | F13: Accepted (with ETA), ready for pickup, reminder, cancelled — including COD cash-ready reminder | G13: Push flows tested | H13: Critical | I13: Not Started | K13: BE-008 | L13: 6
A14: 11 | B14: Phase 8 | C14: W9 | D14: BE-011 | E14: Settlement Engine | F14: Nets Razorpay payables against COD fees owed per vendor, daily or weekly; generates vendor statement PDF | G14: Engine tested | H14: Critical | I14: Not Started | K14: DB-013 | L14: 14
A15: 12 | B15: Phase 8 | C15: W9 | D15: BE-012 | E15: Razorpay Refund API Integration | F15: Automatic full refund for self-cancelled Razorpay orders; exclude both cancellation paths from settlement | G15: Refund flow tested | H15: Critical | I15: Not Started | K15: BE-007 | L15: 6
... A19: 16 | B19: Phase 11 | C19: W12 | D19: BE-016 | E19: Webhook Signature Hardening | F19: Final security pass on Razorpay webhook signature verification before launch | G19: Hardening verified | H19: Critical | I19: Not Started | K19: BE-004 | L19: 4
A21: ="TOTAL TASKS: "&COUNTA(D4:D19)&" | Est. Hours:" -> TOTAL TASKS: 16 | Est. Hours: | L21: =SUM(L4:L19) -> 119

Sheet FlutterFlow
A1: 🔧 FlutterFlow Dev — TakeOnTime App Task Tracker
A2: Customer/Vendor/Admin build, Supabase connect, screens, actions, deploy
A3: # | B3: Phase | C3: Week | D3: Task ID | E3: Task Title | F3: Description | G3: Deliverable / Output | H3: Priority | I3: Status | J3: Assigned To | K3: Depends On | L3: Est. Hours | M3: Actual Hours | N3: Notes
A4: 1 | B4: Phase 0 | C4: W1 | D4: FF-001 | E4: FlutterFlow Project Setup | F4: Create Customer, Vendor, Admin projects/apps; configure theme from design system | G4: Projects live | H4: Critical | I4: Not Started | K4: UX-001 | L4: 6
A5: 2 | B5: Phase 0 | C5: W1 | D5: FF-002 | E5: Connect Supabase & Import Schema | F5: Connect Supabase URL + anon key, import all core tables | G5: Supabase connected | H5: Critical | I5: Not Started | K5: DB-002 | L5: 3
A6: 3 | B6: Phase 1 | C6: W2 | D6: FF-003 | E6: Login/Signup — All Roles | F6: Customer Login/Signup (OTP/Email), Vendor Login/Signup, Admin Login + Profile forms | G6: Auth screens live | H6: Critical | I6: Not Started | K6: BE-002 | L6: 10
A7: 4 | B7: Phase 2 | C7: W3 | D7: FF-004 | E7: Vendor Onboarding Flow | F7: Register → Business Profile → Document Upload → Bank Connect → Branch Setup → Select/Create Org | G7: Vendor onboarding live | H7: Critical | I7: Not Started | K7: UX-004 | L7: 16
A8: 5 | B8: Phase 3 | C8: W4 | D8: FF-005 | E8: Vendor Menu Management | F8: Category Manager, Product Editor, Availability Window Setting, Store & Inventory Toggles | G8: Menu management live | H8: Critical | I8: Not Started | K8: UX-006 | L8: 16
A9: 6 | B9: Phase 4 | C9: W5 | D9: FF-006 | E9: Customer Discovery Screens | F9: Vendor List (search/nearby/category), Menu Screen (time-aware), Product Detail | G9: Discovery live | H9: Critical | I9: Not Started | K9: UX-007 | L9: 14
A10: 7 | B10: Phase 5 | C10: W6 | D10: FF-007 | E10: Cart & Checkout | F10: Cart, Checkout (pickup-time picker), Payment Method Selector | G10: Checkout live | H10: Critical | I10: Not Started | K10: UX-008 | L10: 12
A11: 8 | B11: Phase 5 | C11: W6 | D11: FF-008 | E11: Razorpay Checkout Integration | F11: UPI/Card/Netbanking checkout wired to BE-004; Order Created + Invoice Generated on success | G11: Integration tested | H11: Critical | I11: Not Started | K11: BE-004 | L11: 10
A12: 9 | B12: Phase 5 | C12: W6 | D12: FF-009 | E12: COD Confirmation & Invoice Screen | F12: COD confirmation screen; auto-generated downloadable PDF invoice for both payment paths | G12: Screens live | H12: Critical | I12: Not Started | K12: BE-005 | L12: 6
A13: 10 | B13: Phase 5 | C13: W6 | D13: FF-010 | E13: Self-Cancel Button + Countdown | F13: Cancel Order button with live 2:00 countdown on Confirmation/Tracking screen; disables on deadline/acceptance | G13: Component live + tested | H13: Critical | I13: Not Started | K13: UX-009 | L13: 8
A14: 11 | B14: Phase 6 | C14: W7 | D14: FF-011 | E14: Vendor Kitchen Display | F14: Order Queue sorted by pickup deadline, Accept Order Modal (5/10/15/30 min), Order Card with COD flag | G14: Kitchen display live | H14: Critical | I14: Not Started | K14: UX-011 | L14: 14
A15: 12 | B15: Phase 6 | C15: W7 | D15: FF-012 | E15: Vendor Cancel/Refund Flow | F15: Cancel + Auto-Refund and Cancel + Cash Refund actions on the order card | G15: Flow tested | H15: High | I15: Not Started | K15: FF-011 | L15: 6
... A24: 21 | B24: Phase 11 | C24: W12 | D24: FF-021 | E24: Play Store & App Store Submission | F24: Submit production builds with store listings, screenshots, privacy policy | G24: Apps submitted | H24: Critical | I24: Not Started | K24: FF-020 | L24: 6
A26: ="TOTAL TASKS: "&COUNTA(D4:D24)&" | Est. Hours:" -> TOTAL TASKS: 21 | Est. Hours: | L26: =SUM(L4:L24) -> 201

Sheet QA & Testing
A1: 🧪 QA Engineer — TakeOnTime App Task Tracker
A2: Test plans, functional, regression, payment edge cases
A3: # | B3: Phase | C3: Week | D3: Task ID | E3: Task Title | F3: Description | G3: Deliverable / Output | H3: Priority | I3: Status | J3: Assigned To | K3: Depends On | L3: Est. Hours | M3: Actual Hours | N3: Notes
A4: 1 | B4: Phase 0 | C4: W1 | D4: QA-001 | H4: Critical | I4: Not Started | K4: — | L4: 4
A5: 2 | B5: Phase 1 | C5: W2 | D5: QA-002 | H5: Critical | I5: Not Started | K5: FF-003 | L5: 6
A6: 3 | B6: Phase 2 | C6: W3 | D6: QA-003 | H6: High | I6: Not Started | K6: FF-004 | L6: 6
A7: 4 | B7: Phase 3 | C7: W4 | D7: QA-004 | H7: High | I7: Not Started | K7: FF-005 | L7: 4
A8: 5 | B8: Phase 4 | C8: W5 | D8: QA-005 | H8: High | I8: Not Started | K8: FF-006 | L8: 4
A9: 6 | B9: Phase 5 | C9: W6 | D9: QA-006 | H9: Critical | I9: Not Started | K9: FF-008 | L9: 8
A10: 7 | B10: Phase 5 | C10: W6 | D10: QA-007 | H10: Critical | I10: Not Started | K10: FF-010 | L10: 6
A11: 8 | B11: Phase 6 | C11: W7 | D11: QA-008 | H11: High | I11: Not Started | K11: FF-011 | L11: 6
A12: 9 | B12: Phase 7 | C12: W8 | D12: QA-009 | H12: High | I12: Not Started | K12: FF-014 | L12: 6
A13: 10 | B13: Phase 8 | C13: W9 | D13: QA-010 | H13: Critical | I13: Not Started | K13: BE-011 | L13: 8
A14: 11 | B14: Phase 9 | C14: W10 | D14: QA-011 | H14: Medium | I14: Not Started | K14: FF-016 | L14: 6
A15: 12 | B15: Phase 10 | C15: W11 | D15: QA-012 | H15: Medium | I15: Not Started | K15: FF-018 | L15: 6
... A18: 15 | B18: Phase 11 | C18: W12 | D18: QA-015 | H18: Critical | I18: Not Started | K18: QA-013 | L18: 4
A20: ="TOTAL TASKS: "&COUNTA(D4:D18)&" | Est. Hours:" -> TOTAL TASKS: 15 | Est. Hours: | L20: =SUM(L4:L18) -> 92

Sheet Edge Functions
A1: ⚙️ Edge Functions Catalog — TakeOnTime App
A2: Backend service layer — one Edge Function per business operation
A3: # | B3: Edge Function | C3: Service Module | D3: Trigger | E3: Purpose | F3: Week Built
A4: 1 | B4: send_otp / verify_otp | C4: Authentication Service | D4: Client call | E4: Issue and verify phone/email OTP for all three roles | F4: W2
A5: 2 | B5: create_order | C5: Order Service | D5: Client call (post payment success / COD select) | E5: Validates cart, consumes stock hold, creates order and order_items, deducts inventory., sets cancellable window | F5: W6
A6: 3 | B6: verify_payment | C6: Payment Service | D6: Razorpay webhook | E6: Verifies webhook, matches razorpay_order_id, updates payment, calls create_order. | F6: W6
A7: 4 | B7: create_invoice / generate_pdf | C7: Invoice Service | D7: After create_order | E7: Renders and stores the customer invoice PDF (Razorpay-paid or Pay-at-Pickup) | F7: W6
A8: 5 | B8: cancel_order (self-cancel) | C8: Order Service | D8: Client call (customer, within 2-min window) | E8: Razorpay auto-refund via API or COD void, before vendor acceptance | F8: W6
A9: 6 | B9: create_payment_order | C9: Payment Service | D9: Client Call | E9: Creates Razorpay Order, creates stock hold, writes preliminary payment | F9: W7
A10: 7 | B10: vendor_accept_order | C10: Order Service | D10: Client call (vendor) | E10: Accepts order, sets prep_time_minutes, notifies customer | F10: W7
A11: 8 | B11: cancel_order (vendor-initiated) | C11: Order Service | D11: Client call (vendor) | E11: Vendor cancellation with auto digital refund or manually logged cash refund | F11: W7
A12: 9 | B12: vendor_document_notify | C12: Vendor Service | D12: On document upload | E12: Notifies admin/vendor, updates verification status | F12: W3
A13: 10 | B13: settlement_run | C13: Settlement Service | D13: Cron (daily/weekly) | E13: Nets Razorpay payables vs COD fees owed per vendor, writes vendor_settlements | F13: W9
A14: 11 | B14: send_notifications | C14: Notification Service | D14: Called by other functions | E14: Central FCM fan-out + notifications log writer | F14: W7–W8

Sheet Cron Jobs
A1: ⏰ Cron Jobs / Scheduled Tasks — TakeOnTime App
A2: Scheduled backend execution required beyond request/response Edge Functions
A3: # | B3: Cron Job | C3: Schedule | D3: What It Does | E3: Week Built
A4: 1 | B4: cron_scheduled_orders | C4: Every minute | D4: Auto-sends “Order for Later” orders to the vendor at the correct lead time before pickup | E4: W7
A5: 2 | B5: cleanup_expired_cancellations | C5: Every minute | D5: Flips orders.cancellable to false once customer_cancel_deadline passes | E5: W7
A6: 3 | B6: release_expired_stock_holds | C6: Every minute | D6: Releases expired stock reservations | E6: W8
A7: 4 | B7: settlement_run | C7: Daily or weekly (configurable) | D7: Runs the settlement engine and generates vendor statements | E7: W9
A8: 5 | B8: notification_reminders | C8: Every few minutes | D8: COD pickup reminders, “order ready” nudges not yet acknowledged | E8: W8
A9: 6 | B9: invoice_cleanup | C9: Daily | D9: Removes/archives expired or orphaned invoice files from storage | E9: W12
A10: 7 | B10: analytics_refresh | C10: Hourly | D10: Refreshes materialized views backing the vendor and admin dashboards | E10: W10

Sheet Feature Tracker
A1: 🧵 Feature Tracker (Cross-Layer View) — TakeOnTime App
A2: Every feature traced across Flow, UI, Database, Backend, Edge Function, API, and Testing ]
A3: # | B3: Feature | C3: Flow | D3: UI | E3: Database | F3: Backend | G3: Edge Function | H3: API | I3: Testing
A4: 1 | B4: Authentication (OTP/Email, 3 roles) | C4: Login → Verify → Profile | D4: Login/Signup screens (Customer/Vendor/Admin) | E4: users, device_tokens | F4: Authentication Service | G4: send_otp / verify_otp | H4: — | I4: QA-002
A5: 2 | B5: Vendor Onboarding | C5: Register → Docs → Bank → Branch → Org | D5: Vendor onboarding screens | E5: vendors, vendor_branches, vendor_organizations | F5: Vendor Service | G5: vendor_document_notify | H5: — | I5: QA-003
A6: 3 | B6: Menu Management | C6: Category → Product → Images → Availability | D6: Category Manager, Product Editor | E6: categories, products, product_images | F6: Vendor Service | G6: — | H6: — | I6: QA-004
A7: 4 | B7: Customer Discovery | C7: Org select → Vendor List → Menu → Product | D7: Vendor List, Menu, Product Detail | E7: organizations, vendor_organizations, products (read) | F7: — | G7: — | H7: Geofenced query | I7: QA-005
A8: 5 | B8: Cart & Checkout (Razorpay) | C8: Cart → Checkout → Pay → Order → Invoice | D8: Cart, Checkout, Razorpay Checkout, Invoice | E8: orders, order_items, payments, customer_invoices | F8: Order + Payment + Invoice Services | G8: create_payment_order verify_payment create_order create_invoice | H8: Razorpay Orders/Webhook API | I8: QA-006
A9: 6 | B9: Cart & Checkout (COD) | C9: Cart → Checkout → Order → Invoice (Pay at Pickup) | D9: COD Confirmation Screen, Invoice | E9: orders, order_items, payments, customer_invoices | F9: Order + Invoice Services | G9: create_order, create_invoice | H9: — | I9: QA-006
A10: 7 | B10: Self-Cancellation (2-min window) | C10: Cancel tap → Refund/Void → order_events | D10: Cancel button + countdown | E10: orders (cancel fields), order_events | F10: Order Service | G10: cancel_order | H10: Razorpay Refund API | I10: QA-007
A11: 8 | B11: Scheduled Orders (“Order for Later”) | C11: Save → cron → Auto-send to vendor | D11: Pickup-time picker (Later option) | E11: orders (pickup_time) | F11: Order Service | G11: create_order | H11: — | I11: QA-006 / QA-008
A12: 9 | B12: Vendor Live Order Management | C12: Notify → Accept → Prep → Ready → Collected | D12: Kitchen Display, Accept Modal, Order Card | E12: orders, order_events, notifications | F12: Order + Notification Services | G12: vendor_accept_order, cancel_order, send_notifications | H12: — | I12: QA-008
A13: 10 | B13: Customer Tracking & Pickup | C13: Realtime tracker → ETA → OTP/QR → Collected | D13: Live Tracker, ETA, OTP/QR Screen | E13: orders (otp/qr, collected_at), order_events | F13: Notification Service | G13: send_notifications | H13: Realtime (orders) | I13: QA-009
A14: 11 | B14: Settlement Engine | C14: Cron → Net payables/receivables → Statement | D14: Settlement Statement PDF, Cash Collected button | E14: payments, vendor_settlements, vendor_settlement_items | F14: Settlement Service | G14: settlement_run | H14: Razorpay Payouts (future) | I14: QA-010
A15: 12 | B15: Reports & Dashboards | C15: Aggregate → Filter → Export | D15: Earnings Dashboard, Reports Export, Order History | E15: Aggregation views over orders/payments | F15: Invoice Service | G15: generate_pdf | H15: Reports Export API | I15: QA-011
... A17: 14 | B17: Notifications (FCM, multi-device) | C17: Trigger → Fan-out → Push → Log | D17: Notification Center (Vendor) | E17: notifications, device_tokens | F17: Notification Service | G17: send_notifications | H17: FCM API | I17: QA-008 / QA-009

Sheet updates
A1: 🗄️ New & Planned Tables — TakeOnTime App
A2: Additions beyond the original 13 core table groups
A3: # | B3: Table | C3: Status | D3: Purpose / Replaces
A4: 1 | B4: product_images | C4: MVP (Week 1/4) | D4: Replaces products.image_url — one product can carry a gallery of images
A5: 2 | B5: order_events | C5: MVP (Week 1/6–8) | D5: Replaces relying on orders.status alone — stores full status history (Accepted/Preparing/Ready/Collected/Cancelled) for analytics, audits, support
A6: 3 | B6: device_tokens | C6: MVP (Week 1/2) | D6: Replaces a single FCM token on users — one user can have many devices
A7: 4 | B7: favorite_vendors | C7: Post-MVP | D7: Customer's saved vendors for quick access
A8: 5 | B8: favorite_products | C8: Post-MVP | D8: Customer's saved products — speeds up repeat ordering
A9: 6 | B9: customer_addresses | C9: Post-MVP | D9: Saved addresses; unused for pickup-only MVP but positions the app for future delivery
A10: 7 | B10: support_tickets | C10: Post-MVP | D10: Customer support requests, optionally linked to an order
A11: 8 | B11: vendor_holidays | C11: Post-MVP | D11: Holiday calendar as its own table instead of a field inside vendor_branches
B12: stock_holds | D12: Temporary inventory reservation between stock validation and payment
